example_scripts/__init__.py
example_scripts/awg_standard_single_restart_mode_example.py
example_scripts/awg_trigger_with_pulse_generator_example.py
example_scripts/digitiser_continuous_averaging_fifo_mode_example.py
example_scripts/digitiser_continuous_multi_fifo_mode_example.py
example_scripts/digitiser_finite_multi_fifo_mode_example.py
example_scripts/digitiser_standard_single_mode_example.py
example_scripts/digitiser_star_hub_example_example.py
example_scripts/pulse_generator_example.py
spectrum_gmbh/__init__.py
spectrum_gmbh/py.typed
spectrum_gmbh/pyspcm.py
spectrum_gmbh/py_header/__init__.py
spectrum_gmbh/py_header/regs.py
spectrum_gmbh/py_header/spcerr.py
spectrumdevice/__init__.py
spectrumdevice/_version.py
spectrumdevice/exceptions.py
spectrumdevice/measurement.py
spectrumdevice/py.typed
spectrumdevice/devices/__init__.py
spectrumdevice/devices/spectrum_timestamper.py
spectrumdevice/devices/abstract_device/__init__.py
spectrumdevice/devices/abstract_device/abstract_spectrum_card.py
spectrumdevice/devices/abstract_device/abstract_spectrum_channel.py
spectrumdevice/devices/abstract_device/abstract_spectrum_device.py
spectrumdevice/devices/abstract_device/abstract_spectrum_hub.py
spectrumdevice/devices/abstract_device/abstract_spectrum_io_line.py
spectrumdevice/devices/abstract_device/channel_interfaces.py
spectrumdevice/devices/abstract_device/device_interface.py
spectrumdevice/devices/awg/__init__.py
spectrumdevice/devices/awg/abstract_spectrum_awg.py
spectrumdevice/devices/awg/awg_card.py
spectrumdevice/devices/awg/awg_channel.py
spectrumdevice/devices/awg/awg_interface.py
spectrumdevice/devices/awg/synthesis.py
spectrumdevice/devices/digitiser/__init__.py
spectrumdevice/devices/digitiser/abstract_spectrum_digitiser.py
spectrumdevice/devices/digitiser/digitiser_card.py
spectrumdevice/devices/digitiser/digitiser_channel.py
spectrumdevice/devices/digitiser/digitiser_interface.py
spectrumdevice/devices/digitiser/digitiser_star_hub.py
spectrumdevice-1.2.0.dist-info/LICENSE
spectrumdevice-1.2.0.dist-info/METADATA
spectrumdevice-1.2.0.dist-info/WHEEL
spectrumdevice-1.2.0.dist-info/top_level.txt
spectrumdevice-1.2.0.dist-info/RECORD
