Metadata-Version: 2.1
Name: spectrumdevice
Version: 1.2.0
Summary: A high-level, object-oriented Python library for controlling Spectrum Instrumentation digitisers
Home-page: https://github.com/KCL-BMEIS/spectrumdevice
Author: Christian Baker, Francois Joubert
Author-email: christian.baker@kcl.ac.uk,
License: MIT
Project-URL: Documentation, https://kcl-bmeis.github.io/spectrumdevice/
Project-URL: Source, https://github.com/KCL-BMEIS/spectrumdevice
Project-URL: Tracker, https://github.com/KCL-BMEIS/spectrumdevice/issues
Classifier: Development Status :: 4 - Beta
Classifier: Intended Audience :: Science/Research
Classifier: License :: OSI Approved :: MIT License
Classifier: Natural Language :: English
Classifier: Operating System :: POSIX :: Linux
Classifier: Operating System :: Microsoft :: Windows :: Windows 10
Classifier: Operating System :: MacOS :: MacOS X
Classifier: Programming Language :: Python :: 3.10
Classifier: Programming Language :: Python :: 3.11
Classifier: Programming Language :: Python :: 3.12
Classifier: Topic :: Scientific/Engineering
Classifier: Typing :: Typed
Requires-Python: >=3.10
License-File: LICENSE
Requires-Dist: numpy >=1.26.2
Provides-Extra: dev
Requires-Dist: flake8 ==6.1.0 ; extra == 'dev'
Requires-Dist: flake8-bugbear ==23.9.16 ; extra == 'dev'
Requires-Dist: black ==22.3.0 ; extra == 'dev'
Requires-Dist: mypy ==1.6.1 ; extra == 'dev'
Requires-Dist: types-setuptools ==67.8.0.0 ; extra == 'dev'
Provides-Extra: doc
Requires-Dist: pdoc ==14.5.1 ; extra == 'doc'
Provides-Extra: examples
Requires-Dist: matplotlib >=3.5.0 ; extra == 'examples'
Provides-Extra: test
Requires-Dist: pytest ==7.4.3 ; extra == 'test'
